[{"line":1,"elements":[{"start_timestamp":"2022-01-26T05:08:33.225Z","before":[{"result":{"duration":1845000000,"status":"passed"},"match":{"location":"mainPackage.StepsDefinitions.Hooks.setup()"}}],"line":3,"name":"Get the data for sept.2021","description":"","id":"go-to-google-finance-and-derive-data-for-certain-dates;get-the-data-for-sept.2021","after":[{"result":{"duration":686000000,"status":"passed"},"match":{"location":"mainPackage.StepsDefinitions.Hooks.tearDown(io.cucumber.java.Scenario)"}}],"type":"scenario","keyword":"Scenario","steps":[{"result":{"duration":4653000000,"status":"passed"},"line":4,"name":"the user wants to navigate to google finance","match":{"location":"mainPackage.StepsDefinitions.StepsDefinition.the_user_wants_to_navigate_to_google_finance()"},"keyword":"Given "},{"result":{"duration":809000000,"status":"passed"},"line":5,"name":"the user wants to get the page for google's shares on stock market","match":{"location":"mainPackage.StepsDefinitions.StepsDefinition.the_user_wants_to_get_the_page_for_google_s_shares_on_stock_market()"},"keyword":"Then "},{"result":{"duration":1941000000,"status":"passed"},"line":6,"name":"the user wants to get the data for sep2021","match":{"location":"mainPackage.StepsDefinitions.StepsDefinition.the_user_wants_to_get_the_data_for_sep2021()"},"keyword":"And "},{"result":{"duration":507000000,"status":"passed"},"line":7,"name":"the user wants to get the data for june2021","match":{"location":"mainPackage.StepsDefinitions.StepsDefinition.the_user_wants_to_get_the_data_for_june2021()"},"keyword":"And "},{"result":{"duration":492000000,"status":"passed"},"line":8,"name":"the user wants to get the data for mar2021","match":{"location":"mainPackage.StepsDefinitions.StepsDefinition.the_user_wants_to_get_the_data_for_mar2021()"},"keyword":"And "},{"result":{"duration":514000000,"status":"passed"},"line":9,"name":"the user wants to get the data for dec2021","match":{"location":"mainPackage.StepsDefinitions.StepsDefinition.the_user_wants_to_get_the_data_for_dec2021()"},"keyword":"And "},{"result":{"duration":472000000,"status":"passed"},"line":10,"name":"the user wants to get the data for sep2020","match":{"location":"mainPackage.StepsDefinitions.StepsDefinition.the_user_wants_to_get_the_data_for_sep2020()"},"keyword":"And "},{"result":{"duration":74000000,"status":"passed"},"line":11,"name":"the user wants to verify that Cost of Revenue for Sep2020 equals \"21.12B\"","match":{"arguments":[{"val":"\"21.12B\"","offset":65}],"location":"mainPackage.StepsDefinitions.StepsDefinition.the_user_wants_to_verify_that_cost_of_revenue_for_sep2020_equals(java.lang.String)"},"keyword":"And "}],"tags":[{"name":"@Test1"}]}],"name":"Go to google Finance and derive data for certain dates","description":"","id":"go-to-google-finance-and-derive-data-for-certain-dates","keyword":"Feature","uri":"file:src/test/java/mainPackage/Features/finance.feature","tags":[]}]